.DS_Store
allesfitter/.DS_Store
allesfitter/GUI.ipynb
allesfitter/GUI_tess_transit_search.ipynb
allesfitter/LOGO_circ.png
allesfitter/__init__.py
allesfitter/__init__.pyc
allesfitter/basement.py
allesfitter/basement.pyc
allesfitter/class.py
allesfitter/computer.py
allesfitter/computer.pyc
allesfitter/config.py
allesfitter/config.pyc
allesfitter/constants.py
allesfitter/deriver.py
allesfitter/deriver.pyc
allesfitter/general_output.py
allesfitter/general_output.pyc
allesfitter/generative_models.py
allesfitter/generator.py
allesfitter/inout.py
allesfitter/io.py
allesfitter/lightcurves.py
allesfitter/mcmc.py
allesfitter/mcmc.pyc
allesfitter/mcmc_output.py
allesfitter/mcmc_output.pyc
allesfitter/nested_sampling.py
allesfitter/nested_sampling.pyc
allesfitter/nested_sampling_output.py
allesfitter/nested_sampling_output.pyc
allesfitter/observables.py
allesfitter/plot_top_down_view.py
allesfitter/plotter.py
allesfitter/plotting.py
allesfitter/prepare_ttv_fit.py
allesfitter/run.py
allesfitter/simulate.py
allesfitter/spots.py
allesfitter/spots.pyc
allesfitter/statistics.py
allesfitter/time_series.py
allesfitter/translator.py
allesfitter/.ipynb_checkpoints/GUI-checkpoint.ipynb
allesfitter/.ipynb_checkpoints/GUI_tess_transit_search-checkpoint.ipynb
allesfitter/.ipynb_checkpoints/Untitled-checkpoint.ipynb
allesfitter/__pycache__/__init__.cpython-36.pyc
allesfitter/__pycache__/__init__.cpython-37.pyc
allesfitter/__pycache__/__init__.cpython-38.pyc
allesfitter/__pycache__/__init__.cpython-39.pyc
allesfitter/__pycache__/allesclass2.cpython-37.pyc
allesfitter/__pycache__/basement.cpython-36.pyc
allesfitter/__pycache__/basement.cpython-37.pyc
allesfitter/__pycache__/basement.cpython-38.pyc
allesfitter/__pycache__/basement.cpython-39.pyc
allesfitter/__pycache__/classes.cpython-37.pyc
allesfitter/__pycache__/computer.cpython-37.pyc
allesfitter/__pycache__/computer.cpython-38.pyc
allesfitter/__pycache__/computer.cpython-39.pyc
allesfitter/__pycache__/config.cpython-36.pyc
allesfitter-1.2.10.dist-info/LICENSE.txt
allesfitter-1.2.10.dist-info/METADATA
allesfitter-1.2.10.dist-info/WHEEL
allesfitter-1.2.10.dist-info/top_level.txt
allesfitter-1.2.10.dist-info/RECORD
