Metadata-Version: 2.1
Name: allesfitter
Version: 1.2.10
Summary: A global inference framework for photometry and RV
Home-page: https://github.com/MNGuenther/allesfitter
Download-URL: https://github.com/MNGuenther/allesfitter
Author: Maximilian N. Günther & Tansu Daylan
Author-email: maximilian.guenther@esa.int
License: MIT
Platform: UNKNOWN
Classifier: Development Status :: 5 - Production/Stable
Classifier: Intended Audience :: Science/Research
Classifier: License :: OSI Approved :: MIT License
Classifier: Programming Language :: Python
License-File: LICENSE.txt
